{
  "name": "Code",
  "type": "Component",
  "tiers": "Global",
  "documentationStatus": "Needs work",
  "lastEdited": "Nov 24, 2025",
  "figmaLink": "",
  "codeLink": "",
  "figmaComponentDataPath": "",
  "componentExampleImage": "",
  "changeLog": [
    {
      "who": "Maximilian Blazek",
      "when": "2025-11-21T17:00:00.000+00:00",
      "what": "Initial commit"
    }
  ],
  "decisionLog": [],
  "properties": [],
  "anatomy": {
    "image": "md/code/images/2a32fbc4-6c67-4403-add4-370aad91796d.png",
    "table": []
  }
}