{
  "name": "Quote wrapper",
  "slug": "quote-wrapper",
  "type": "Pattern",
  "tiers": "Sites",
  "documentationStatus": "Needs work",
  "lastEdited": "2026-02-10T08:16:36.803+00:00",
  "figmaLink": "",
  "codeLink": "",
  "description": "",
  "usage": "",
  "examples": "",
  "interactions": "",
  "figmaComponentData": "",
  "componentExampleImage": "",
  "sitesArchitectureLevels": "i-ues18YVwia",
  "properties": [
    {
      "name": "Section rule",
      "required": true,
      "type": "object",
      "description": "The rule component indicates the beginning of a new pattern",
      "constraint": "Only use the default style for the section-level rule",
      "defaultOption": "default",
      "options": [
        "default"
      ]
    },
    {
      "name": "Linked heading",
      "required": false,
      "type": "single select",
      "description": "The heading may function as a link when clearly indicated.",
      "constraint": "",
      "defaultOption": "default",
      "options": [
        "default",
        "link"
      ]
    },
    {
      "name": "Bottom padding",
      "required": true,
      "type": "single select",
      "description": "The type of padding applied to the bottom of the pattern",
      "constraint": "",
      "defaultOption": "default",
      "options": [
        "default",
        "deep",
        "shallow",
        "none"
      ]
    }
  ],
  "changeLog": [],
  "decisionLog": [],
  "appliedRules": [],
  "exceptionFromRules": [
    {
      "rule": "Section title is styled as H2 or Heading muted",
      "ruleStrength": "MUST",
      "status": "Approved",
      "type": "Specific rule",
      "lastEdited": "2026-02-18T09:35:07.035+00:00",
      "appliesToConcepts": [
        "Section",
        "Content primitive"
      ],
      "appliesToConstructs": [],
      "knownExceptionForConstructs": "Hero, Blog, Data spotlight, Logo section, Quote wrapper",
      "knownExceptionForConcepts": "",
      "changeLog": [],
      "decisionLog": []
    }
  ],
  "mentionedIn": [],
  "mentionsComponents": []
}
